templite
