Metadata-Version: 1.1
Name: templite
Version: 0.2.1
Summary: A light-weight, fully functional, general purpose Python templating engine that fits in one single file.
Home-page: http://www.joonis.de/en/code/templite
Author: Sam et Max
Author-email: lesametlemax@gmail.com
License: UNKNOWN
Platform: UNKNOWN
Classifier: Programming Language :: Python
Classifier: Intended Audience :: Information Technology
Classifier: License :: OSI Approved :: GNU General Public License (GPL)
Classifier: Natural Language :: English
Classifier: Programming Language :: Python :: 2.7
